[
  {
    "type": "process_start",
    "process_name": "msedge.exe",
    "process_id": 1688,
    "executable_path": "C:\\Program Files (x86)\\Microsoft\\Edge\\Application\\msedge.exe",
    "command_line": "C:\\Program Files (x86)\\Microsoft\\Edge\\Application\\msedge.exe --type=renderer --extension-process --renderer-sub-type=extension --pdf-upsell-enabled --no-pre-read-main-dll --video-capture-use-gpu-memory-buffer --lang=zh-CN --js-flags=--ms-user-locale= --device-scale-factor=1.5 --num-raster-threads=4 --enable-main-frame-before-activation --renderer-client-id=69 --time-ticks-at-unix-epoch=-1749794626440662 --launch-time-ticks=1301963942395 --always-read-main-dll --field-trial-handle=2408,i,190787146257617024,3102830445832319338,262144 --variations-seed-version --mojo-platform-channel-handle=8172 /prefetch:9",
    "timestamp": "2025-06-28T15:43:10.388028"
  },
  {
    "type": "process_end",
    "process_id": 60184,
    "process_name": "msedge.exe",
    "executable_path": "C:\\Program Files (x86)\\Microsoft\\Edge\\Application\\msedge.exe",
    "timestamp": "2025-06-28T15:43:18.398291"
  },
  {
    "type": "process_end",
    "process_id": 18196,
    "process_name": "msedge.exe",
    "executable_path": "C:\\Program Files (x86)\\Microsoft\\Edge\\Application\\msedge.exe",
    "timestamp": "2025-06-28T15:43:18.398291"
  },
  {
    "type": "process_start",
    "process_name": "msedge.exe",
    "process_id": 8156,
    "executable_path": "C:\\Program Files (x86)\\Microsoft\\Edge\\Application\\msedge.exe",
    "command_line": "C:\\Program Files (x86)\\Microsoft\\Edge\\Application\\msedge.exe --type=renderer --extension-process --renderer-sub-type=extension --pdf-upsell-enabled --no-pre-read-main-dll --video-capture-use-gpu-memory-buffer --lang=zh-CN --js-flags=--ms-user-locale= --device-scale-factor=1.5 --num-raster-threads=4 --enable-main-frame-before-activation --renderer-client-id=71 --time-ticks-at-unix-epoch=-1749794626440662 --launch-time-ticks=1301994982865 --always-read-main-dll --field-trial-handle=2408,i,190787146257617024,3102830445832319338,262144 --variations-seed-version --mojo-platform-channel-handle=3212 /prefetch:9",
    "timestamp": "2025-06-28T15:43:41.429653"
  },
  {
    "type": "process_start",
    "process_name": "msedge.exe",
    "process_id": 29820,
    "executable_path": "C:\\Program Files (x86)\\Microsoft\\Edge\\Application\\msedge.exe",
    "command_line": "C:\\Program Files (x86)\\Microsoft\\Edge\\Application\\msedge.exe --type=renderer --extension-process --renderer-sub-type=extension --pdf-upsell-enabled --no-pre-read-main-dll --video-capture-use-gpu-memory-buffer --lang=zh-CN --js-flags=--ms-user-locale= --device-scale-factor=1.5 --num-raster-threads=4 --enable-main-frame-before-activation --renderer-client-id=70 --time-ticks-at-unix-epoch=-1749794626440662 --launch-time-ticks=1301994336109 --always-read-main-dll --field-trial-handle=2408,i,190787146257617024,3102830445832319338,262144 --variations-seed-version --mojo-platform-channel-handle=8708 /prefetch:9",
    "timestamp": "2025-06-28T15:43:40.782941"
  },
  {
    "type": "process_end",
    "process_id": 1688,
    "process_name": "msedge.exe",
    "executable_path": "C:\\Program Files (x86)\\Microsoft\\Edge\\Application\\msedge.exe",
    "timestamp": "2025-06-28T15:43:51.715037"
  },
  {
    "type": "process_end",
    "process_id": 8156,
    "process_name": "msedge.exe",
    "executable_path": "C:\\Program Files (x86)\\Microsoft\\Edge\\Application\\msedge.exe",
    "timestamp": "2025-06-28T15:44:18.447108"
  },
  {
    "type": "process_end",
    "process_id": 29820,
    "process_name": "msedge.exe",
    "executable_path": "C:\\Program Files (x86)\\Microsoft\\Edge\\Application\\msedge.exe",
    "timestamp": "2025-06-28T15:44:18.447108"
  },
  {
    "type": "process_start",
    "process_name": "msedge.exe",
    "process_id": 42332,
    "executable_path": "C:\\Program Files (x86)\\Microsoft\\Edge\\Application\\msedge.exe",
    "command_line": "C:\\Program Files (x86)\\Microsoft\\Edge\\Application\\msedge.exe --type=renderer --extension-process --renderer-sub-type=extension --pdf-upsell-enabled --no-pre-read-main-dll --video-capture-use-gpu-memory-buffer --lang=zh-CN --js-flags=--ms-user-locale= --device-scale-factor=1.5 --num-raster-threads=4 --enable-main-frame-before-activation --renderer-client-id=72 --time-ticks-at-unix-epoch=-1749794626440662 --launch-time-ticks=1302024693782 --always-read-main-dll --field-trial-handle=2408,i,190787146257617024,3102830445832319338,262144 --variations-seed-version --mojo-platform-channel-handle=8832 /prefetch:9",
    "timestamp": "2025-06-28T15:44:11.139159"
  },
  {
    "type": "process_end",
    "process_id": 42332,
    "process_name": "msedge.exe",
    "executable_path": "C:\\Program Files (x86)\\Microsoft\\Edge\\Application\\msedge.exe",
    "timestamp": "2025-06-28T15:44:44.297280"
  },
  {
    "type": "process_start",
    "process_name": "msedge.exe",
    "process_id": 24884,
    "executable_path": "C:\\Program Files (x86)\\Microsoft\\Edge\\Application\\msedge.exe",
    "command_line": "C:\\Program Files (x86)\\Microsoft\\Edge\\Application\\msedge.exe --type=renderer --extension-process --renderer-sub-type=extension --pdf-upsell-enabled --no-pre-read-main-dll --video-capture-use-gpu-memory-buffer --lang=zh-CN --js-flags=--ms-user-locale= --device-scale-factor=1.5 --num-raster-threads=4 --enable-main-frame-before-activation --renderer-client-id=74 --time-ticks-at-unix-epoch=-1749794626440662 --launch-time-ticks=1302055016922 --always-read-main-dll --field-trial-handle=2408,i,190787146257617024,3102830445832319338,262144 --variations-seed-version --mojo-platform-channel-handle=9068 /prefetch:9",
    "timestamp": "2025-06-28T15:44:41.462542"
  },
  {
    "type": "process_start",
    "process_name": "msedge.exe",
    "process_id": 26956,
    "executable_path": "C:\\Program Files (x86)\\Microsoft\\Edge\\Application\\msedge.exe",
    "command_line": "C:\\Program Files (x86)\\Microsoft\\Edge\\Application\\msedge.exe --type=renderer --extension-process --renderer-sub-type=extension --pdf-upsell-enabled --no-pre-read-main-dll --video-capture-use-gpu-memory-buffer --lang=zh-CN --js-flags=--ms-user-locale= --device-scale-factor=1.5 --num-raster-threads=4 --enable-main-frame-before-activation --renderer-client-id=73 --time-ticks-at-unix-epoch=-1749794626440662 --launch-time-ticks=1302054981246 --always-read-main-dll --field-trial-handle=2408,i,190787146257617024,3102830445832319338,262144 --variations-seed-version --mojo-platform-channel-handle=8760 /prefetch:9",
    "timestamp": "2025-06-28T15:44:41.427822"
  },
  {
    "type": "window_focus",
    "window_title": "integrated_monitor.py - MEMO - Cursor",
    "process_name": "Cursor.exe",
    "process_id": 1728,
    "executable_path": "C:\\Users\\yuwy\\AppData\\Local\\Programs\\cursor\\Cursor.exe",
    "timestamp": "2025-06-28T15:44:53.947818"
  },
  {
    "type": "app_usage",
    "process_name": "WeChat.exe",
    "duration": 477.54,
    "timestamp": "2025-06-28T15:44:53.947818"
  },
  {
    "type": "process_end",
    "process_id": 24884,
    "process_name": "msedge.exe",
    "executable_path": "C:\\Program Files (x86)\\Microsoft\\Edge\\Application\\msedge.exe",
    "timestamp": "2025-06-28T15:45:12.666932"
  },
  {
    "type": "process_start",
    "process_name": "msedge.exe",
    "process_id": 27956,
    "executable_path": "C:\\Program Files (x86)\\Microsoft\\Edge\\Application\\msedge.exe",
    "command_line": "C:\\Program Files (x86)\\Microsoft\\Edge\\Application\\msedge.exe --type=renderer --extension-process --renderer-sub-type=extension --pdf-upsell-enabled --no-pre-read-main-dll --video-capture-use-gpu-memory-buffer --lang=zh-CN --js-flags=--ms-user-locale= --device-scale-factor=1.5 --num-raster-threads=4 --enable-main-frame-before-activation --renderer-client-id=75 --time-ticks-at-unix-epoch=-1749794626440662 --launch-time-ticks=1302085416741 --always-read-main-dll --field-trial-handle=2408,i,190787146257617024,3102830445832319338,262144 --variations-seed-version --mojo-platform-channel-handle=7856 /prefetch:9",
    "timestamp": "2025-06-28T15:45:11.862658"
  },
  {
    "type": "process_start",
    "process_name": "LeASPac.exe",
    "process_id": 35212,
    "executable_path": "C:\\Program Files (x86)\\Lenovo\\LeAppStore\\LeASPac.exe",
    "command_line": "C:\\Program Files (x86)\\Lenovo\\LeAppStore\\LeASPac.exe -timer",
    "timestamp": "2025-06-28T15:45:29.785262"
  },
  {
    "type": "process_end",
    "process_id": 35212,
    "process_name": "LeASPac.exe",
    "executable_path": "C:\\Program Files (x86)\\Lenovo\\LeAppStore\\LeASPac.exe",
    "timestamp": "2025-06-28T15:45:37.506870"
  },
  {
    "type": "process_end",
    "process_id": 27956,
    "process_name": "msedge.exe",
    "executable_path": "C:\\Program Files (x86)\\Microsoft\\Edge\\Application\\msedge.exe",
    "timestamp": "2025-06-28T15:45:44.428799"
  },
  {
    "type": "process_start",
    "process_name": "msedge.exe",
    "process_id": 40232,
    "executable_path": "C:\\Program Files (x86)\\Microsoft\\Edge\\Application\\msedge.exe",
    "command_line": "C:\\Program Files (x86)\\Microsoft\\Edge\\Application\\msedge.exe --type=renderer --extension-process --renderer-sub-type=extension --pdf-upsell-enabled --no-pre-read-main-dll --video-capture-use-gpu-memory-buffer --lang=zh-CN --js-flags=--ms-user-locale= --device-scale-factor=1.5 --num-raster-threads=4 --enable-main-frame-before-activation --renderer-client-id=76 --time-ticks-at-unix-epoch=-1749794626440662 --launch-time-ticks=1302115846074 --always-read-main-dll --field-trial-handle=2408,i,190787146257617024,3102830445832319338,262144 --variations-seed-version --mojo-platform-channel-handle=10120 /prefetch:9",
    "timestamp": "2025-06-28T15:45:42.291592"
  },
  {
    "type": "process_end",
    "process_id": 26956,
    "process_name": "msedge.exe",
    "executable_path": "C:\\Program Files (x86)\\Microsoft\\Edge\\Application\\msedge.exe",
    "timestamp": "2025-06-28T15:46:12.168896"
  },
  {
    "type": "process_start",
    "process_name": "msedge.exe",
    "process_id": 28608,
    "executable_path": "C:\\Program Files (x86)\\Microsoft\\Edge\\Application\\msedge.exe",
    "command_line": "C:\\Program Files (x86)\\Microsoft\\Edge\\Application\\msedge.exe --type=renderer --extension-process --renderer-sub-type=extension --pdf-upsell-enabled --no-pre-read-main-dll --video-capture-use-gpu-memory-buffer --lang=zh-CN --js-flags=--ms-user-locale= --device-scale-factor=1.5 --num-raster-threads=4 --enable-main-frame-before-activation --renderer-client-id=77 --time-ticks-at-unix-epoch=-1749794626440662 --launch-time-ticks=1302146163546 --always-read-main-dll --field-trial-handle=2408,i,190787146257617024,3102830445832319338,262144 --variations-seed-version --mojo-platform-channel-handle=5264 /prefetch:9",
    "timestamp": "2025-06-28T15:46:12.608776"
  },
  {
    "type": "process_end",
    "process_id": 40232,
    "process_name": "msedge.exe",
    "executable_path": "C:\\Program Files (x86)\\Microsoft\\Edge\\Application\\msedge.exe",
    "timestamp": "2025-06-28T15:46:15.687775"
  },
  {
    "type": "process_end",
    "process_id": 28608,
    "process_name": "msedge.exe",
    "executable_path": "C:\\Program Files (x86)\\Microsoft\\Edge\\Application\\msedge.exe",
    "timestamp": "2025-06-28T15:46:43.560582"
  },
  {
    "type": "process_start",
    "process_name": "msedge.exe",
    "process_id": 56856,
    "executable_path": "C:\\Program Files (x86)\\Microsoft\\Edge\\Application\\msedge.exe",
    "command_line": "C:\\Program Files (x86)\\Microsoft\\Edge\\Application\\msedge.exe --type=renderer --extension-process --renderer-sub-type=extension --pdf-upsell-enabled --no-pre-read-main-dll --video-capture-use-gpu-memory-buffer --lang=zh-CN --js-flags=--ms-user-locale= --device-scale-factor=1.5 --num-raster-threads=4 --enable-main-frame-before-activation --renderer-client-id=78 --time-ticks-at-unix-epoch=-1749794626440662 --launch-time-ticks=1302174983674 --always-read-main-dll --field-trial-handle=2408,i,190787146257617024,3102830445832319338,262144 --variations-seed-version --mojo-platform-channel-handle=10192 /prefetch:9",
    "timestamp": "2025-06-28T15:46:41.426954"
  },
  {
    "type": "process_start",
    "process_name": "msedge.exe",
    "process_id": 61328,
    "executable_path": "C:\\Program Files (x86)\\Microsoft\\Edge\\Application\\msedge.exe",
    "command_line": "C:\\Program Files (x86)\\Microsoft\\Edge\\Application\\msedge.exe --type=renderer --extension-process --renderer-sub-type=extension --pdf-upsell-enabled --no-pre-read-main-dll --video-capture-use-gpu-memory-buffer --lang=zh-CN --js-flags=--ms-user-locale= --device-scale-factor=1.5 --num-raster-threads=4 --enable-main-frame-before-activation --renderer-client-id=79 --time-ticks-at-unix-epoch=-1749794626440662 --launch-time-ticks=1302176551921 --always-read-main-dll --field-trial-handle=2408,i,190787146257617024,3102830445832319338,262144 --variations-seed-version --mojo-platform-channel-handle=6488 /prefetch:9",
    "timestamp": "2025-06-28T15:46:42.997614"
  },
  {
    "type": "process_end",
    "process_id": 56856,
    "process_name": "msedge.exe",
    "executable_path": "C:\\Program Files (x86)\\Microsoft\\Edge\\Application\\msedge.exe",
    "timestamp": "2025-06-28T15:47:14.973712"
  },
  {
    "type": "process_end",
    "process_id": 61328,
    "process_name": "msedge.exe",
    "executable_path": "C:\\Program Files (x86)\\Microsoft\\Edge\\Application\\msedge.exe",
    "timestamp": "2025-06-28T15:47:14.973712"
  },
  {
    "type": "process_start",
    "process_name": "msedge.exe",
    "process_id": 41008,
    "executable_path": "C:\\Program Files (x86)\\Microsoft\\Edge\\Application\\msedge.exe",
    "command_line": "C:\\Program Files (x86)\\Microsoft\\Edge\\Application\\msedge.exe --type=renderer --extension-process --renderer-sub-type=extension --pdf-upsell-enabled --no-pre-read-main-dll --video-capture-use-gpu-memory-buffer --lang=zh-CN --js-flags=--ms-user-locale= --device-scale-factor=1.5 --num-raster-threads=4 --enable-main-frame-before-activation --renderer-client-id=80 --time-ticks-at-unix-epoch=-1749794626440662 --launch-time-ticks=1302206913394 --always-read-main-dll --field-trial-handle=2408,i,190787146257617024,3102830445832319338,262144 --variations-seed-version --mojo-platform-channel-handle=7740 /prefetch:9",
    "timestamp": "2025-06-28T15:47:13.359380"
  },
  {
    "type": "window_focus",
    "window_title": "activity_monitor.py - MEMO - Cursor",
    "process_name": "Cursor.exe",
    "process_id": 1728,
    "executable_path": "C:\\Users\\yuwy\\AppData\\Local\\Programs\\cursor\\Cursor.exe",
    "timestamp": "2025-06-28T15:47:40.363775"
  },
  {
    "type": "process_start",
    "process_name": "msedge.exe",
    "process_id": 18628,
    "executable_path": "C:\\Program Files (x86)\\Microsoft\\Edge\\Application\\msedge.exe",
    "command_line": "C:\\Program Files (x86)\\Microsoft\\Edge\\Application\\msedge.exe --type=renderer --extension-process --renderer-sub-type=extension --pdf-upsell-enabled --no-pre-read-main-dll --video-capture-use-gpu-memory-buffer --lang=zh-CN --js-flags=--ms-user-locale= --device-scale-factor=1.5 --num-raster-threads=4 --enable-main-frame-before-activation --renderer-client-id=82 --time-ticks-at-unix-epoch=-1749794626440662 --launch-time-ticks=1302237313240 --always-read-main-dll --field-trial-handle=2408,i,190787146257617024,3102830445832319338,262144 --variations-seed-version --mojo-platform-channel-handle=10156 /prefetch:9",
    "timestamp": "2025-06-28T15:47:43.761162"
  },
  {
    "type": "process_start",
    "process_name": "msedge.exe",
    "process_id": 24276,
    "executable_path": "C:\\Program Files (x86)\\Microsoft\\Edge\\Application\\msedge.exe",
    "command_line": "C:\\Program Files (x86)\\Microsoft\\Edge\\Application\\msedge.exe --type=renderer --extension-process --renderer-sub-type=extension --pdf-upsell-enabled --no-pre-read-main-dll --video-capture-use-gpu-memory-buffer --lang=zh-CN --js-flags=--ms-user-locale= --device-scale-factor=1.5 --num-raster-threads=4 --enable-main-frame-before-activation --renderer-client-id=81 --time-ticks-at-unix-epoch=-1749794626440662 --launch-time-ticks=1302234993251 --always-read-main-dll --field-trial-handle=2408,i,190787146257617024,3102830445832319338,262144 --variations-seed-version --mojo-platform-channel-handle=10184 /prefetch:9",
    "timestamp": "2025-06-28T15:47:41.441682"
  },
  {
    "type": "process_end",
    "process_id": 41008,
    "process_name": "msedge.exe",
    "executable_path": "C:\\Program Files (x86)\\Microsoft\\Edge\\Application\\msedge.exe",
    "timestamp": "2025-06-28T15:47:46.556725"
  }
]